cross_platform_folder_picker/__init__.py
cross_platform_folder_picker/bases/__init__.py
cross_platform_folder_picker/bases/_abstract.py
cross_platform_folder_picker/bases/gtk.py
cross_platform_folder_picker/bases/linux.py
cross_platform_folder_picker/bases/macos.py
cross_platform_folder_picker/bases/qt.py
cross_platform_folder_picker/bases/tkinter.py
cross_platform_folder_picker/bases/windows.py
cross_platform_folder_picker-0.0.6.dist-info/METADATA
cross_platform_folder_picker-0.0.6.dist-info/WHEEL
cross_platform_folder_picker-0.0.6.dist-info/licenses/LICENSE
cross_platform_folder_picker-0.0.6.dist-info/RECORD
