Metadata-Version: 2.4
Name: cross_platform_folder_picker
Version: 0.0.6
Summary:  A (near zero dependency by default) cross platform folder picker
Project-URL: Homepage, https://github.com/baseplate-admin/Cross-Platform-Folder-Picker
Project-URL: Repository, https://github.com/baseplate-admin/Cross-Platform-Folder-Picker
Project-URL: Bug Tracker, https://github.com/baseplate-admin/Cross-Platform-Folder-Picker/issues
License: MIT
License-File: LICENSE
Classifier: Programming Language :: Python
Classifier: Programming Language :: Python :: 3
Classifier: Programming Language :: Python :: 3.10
Classifier: Programming Language :: Python :: 3.11
Classifier: Programming Language :: Python :: 3.12
Classifier: Programming Language :: Python :: 3.13
Classifier: Programming Language :: Python :: 3.14
Classifier: Programming Language :: Python :: Implementation :: CPython
Classifier: Programming Language :: Python :: Implementation :: PyPy
Classifier: Topic :: Software Development :: Libraries :: Python Modules
Requires-Python: >=3.10
Provides-Extra: gtk
Requires-Dist: pygobject; extra == 'gtk'
Provides-Extra: qt
Requires-Dist: pyside6; extra == 'qt'
